mlops_test_repo/__init__.py
mlops_test_repo/config.py
mlops_test_repo/dataset.py
mlops_test_repo/features.py
mlops_test_repo/plots.py
mlops_test_repo/sample.py
mlops_test_repo/utils.py
mlops_test_repo/entities/__init__.py
mlops_test_repo/entities/data_params.py
mlops_test_repo/entities/feature_params.py
mlops_test_repo/entities/params.py
mlops_test_repo/entities/sql_params.py
mlops_test_repo/entities/train_params.py
mlops_test_repo/examples/01_check_pylint.py
mlops_test_repo/examples/02_load_yaml_file.py
mlops_test_repo/examples/03_load_yaml_file_dataclass.py
mlops_test_repo/examples/04_clearml.py
mlops_test_repo/inference/__init__.py
mlops_test_repo/inference/batch_inference.py
mlops_test_repo/inference/make_requests.py
mlops_test_repo/inference/online_inference.py
mlops_test_repo/modeling/__init__.py
mlops_test_repo/modeling/predict.py
mlops_test_repo/modeling/train.py
mlops_test_repo-0.0.1.dist-info/WHEEL
mlops_test_repo-0.0.1.dist-info/METADATA
mlops_test_repo-0.0.1.dist-info/RECORD
