Metadata-Version: 2.1
Name: mlops_test_repo
Version: 0.0.1
Summary: Repo made with cookiecutter for MLOps NUST MISIS course
Author: Alexey Myshlyanov
Requires-Python: ~=3.9
Classifier: Programming Language :: Python :: 3
